[
    {
        "id": "2511403",
        "channel": "FX Movie Channel",
        "link": "https://list.iptvcat.com/my_list/s/107f2c1c5800cfaf49d63da282274956.m3u8",
        "country": "brazil",
        "liveliness": "32",
        "status": "offline",
        "lastChecked": "2022-04-28T00:00:00Z",
        "format": "hd",
        "mbps": "5991",
        "URI": [
            "s"
        ]
    },
    {
        "id": "2511567",
        "channel": "HDNET MOVIES",
        "link": "https://list.iptvcat.com/my_list/s/cd0203fef2448f2e053314942139a91b.m3u8",
        "country": "brazil",
        "liveliness": "45",
        "status": "online",
        "lastChecked": "2022-04-28T00:00:00Z",
        "format": "fhd 2k",
        "mbps": "13311",
        "URI": [
            "s"
        ]
    },
    {
        "id": "1186562",
        "channel": "Ocko Star",
        "link": "https://list.iptvcat.com/my_list/s/61b2803e325cafff97dbf96853413445.m3u8",
        "country": "brazil",
        "liveliness": "100",
        "status": "online",
        "lastChecked": "2022-04-28T00:00:00Z",
        "format": "sd",
        "mbps": "2098, ...",
        "URI": [
            "s"
        ]
    },
    {
        "id": "2512454",
        "channel": "HBO",
        "link": "https://list.iptvcat.com/my_list/s/69411123a89beb8e618eb46aacf6b72c.m3u8",
        "country": "brazil",
        "liveliness": "77",
        "status": "offline",
        "lastChecked": "2022-04-28T00:00:00Z",
        "format": "hd",
        "mbps": "3795",
        "URI": [
            "s"
        ]
    },
    {
        "id": "2512636",
        "channel": "HBO",
        "link": "https://list.iptvcat.com/my_list/s/c24295b95b362f0d54c1c2b339c34837.m3u8",
        "country": "brazil",
        "liveliness": "91",
        "status": "offline",
        "lastChecked": "2022-04-28T00:00:00Z",
        "format": "fhd 2k",
        "mbps": "13324",
        "URI": [
            "s"
        ]
    },
    {
        "id": "2512455",
        "channel": "HBO 2",
        "link": "https://list.iptvcat.com/my_list/s/4e5aa8c6846a3638f9009ac3eae05de4.m3u8",
        "country": "brazil",
        "liveliness": "77",
        "status": "offline",
        "lastChecked": "2022-04-28T00:00:00Z",
        "format": "fhd 2k",
        "mbps": "13324",
        "URI": [
            "s"
        ]
    },
    {
        "id": "2512637",
        "channel": "HBO 2",
        "link": "https://list.iptvcat.com/my_list/s/8d873e515a94f9d1041eaffd0b5ba78a.m3u8",
        "country": "brazil",
        "liveliness": "91",
        "status": "offline",
        "lastChecked": "2022-04-28T00:00:00Z",
        "format": "fhd 2k",
        "mbps": "13324",
        "URI": [
            "s"
        ]
    },
    {
        "id": "2484988",
        "channel": "HBO 2 HD",
        "link": "https://list.iptvcat.com/my_list/s/54a7a7a6b1a21d9c46d23d9b6fd52e04.m3u8",
        "country": "brazil",
        "liveliness": "96",
        "status": "online",
        "lastChecked": "2022-04-28T00:00:00Z",
        "format": "hd",
        "mbps": "3795",
        "URI": [
            "s"
        ]
    },
    {
        "id": "2485068",
        "channel": "HBO Extreme HD",
        "link": "https://list.iptvcat.com/my_list/s/fdc8b932396cba2ff0cb01f88136ec3d.m3u8",
        "country": "brazil",
        "liveliness": "98",
        "status": "online",
        "lastChecked": "2022-04-28T00:00:00Z",
        "format": "hd",
        "mbps": "3799",
        "URI": [
            "s"
        ]
    },
    {
        "id": "2512638",
        "channel": "HBO FAMILY",
        "link": "https://list.iptvcat.com/my_list/s/f90ff9159f9469c7a7c16e3bb6585e58.m3u8",
        "country": "brazil",
        "liveliness": "91",
        "status": "offline",
        "lastChecked": "2022-04-28T00:00:00Z",
        "format": "fhd 2k",
        "mbps": "13324",
        "URI": [
            "s"
        ]
    },
    {
        "id": "2512456",
        "channel": "HBO FAMILY",
        "link": "https://list.iptvcat.com/my_list/s/a9e261d21df4ee5248df75bfccccd233.m3u8",
        "country": "brazil",
        "liveliness": "55",
        "status": "online",
        "lastChecked": "2022-04-28T00:00:00Z",
        "format": "hd",
        "mbps": "3795",
        "URI": [
            "s"
        ]
    },
    {
        "id": "2485004",
        "channel": "HBO Family HD",
        "link": "https://list.iptvcat.com/my_list/s/0784d24bba3511a45b0bab1439115576.m3u8",
        "country": "brazil",
        "liveliness": "96",
        "status": "online",
        "lastChecked": "2022-04-28T00:00:00Z",
        "format": "hd",
        "mbps": "3799",
        "URI": [
            "s"
        ]
    },
    {
        "id": "2485014",
        "channel": "HBO HD",
        "link": "https://list.iptvcat.com/my_list/s/1a675824d12b30e0b36fbf07d9d4a097.m3u8",
        "country": "brazil",
        "liveliness": "98",
        "status": "online",
        "lastChecked": "2022-04-28T00:00:00Z",
        "format": "hd",
        "mbps": "3799",
        "URI": [
            "s"
        ]
    },
    {
        "id": "2485051",
        "channel": "HBO Mundi HD",
        "link": "https://list.iptvcat.com/my_list/s/4f562f0b1fc29f184c8fe05f108baf09.m3u8",
        "country": "brazil",
        "liveliness": "96",
        "status": "online",
        "lastChecked": "2022-04-28T00:00:00Z",
        "format": "hd",
        "mbps": "3799",
        "URI": [
            "s"
        ]
    },
    {
        "id": "2512639",
        "channel": "HBO PLUS",
        "link": "https://list.iptvcat.com/my_list/s/93e983b94503b7e327a37c945a7e8253.m3u8",
        "country": "brazil",
        "liveliness": "92",
        "status": "offline",
        "lastChecked": "2022-04-28T00:00:00Z",
        "format": "sd",
        "mbps": "2089",
        "URI": [
            "s"
        ]
    },
    {
        "id": "2485026",
        "channel": "HBO Plus HD",
        "link": "https://list.iptvcat.com/my_list/s/8e453bef77f8618d253bc197de30f2c2.m3u8",
        "country": "brazil",
        "liveliness": "98",
        "status": "online",
        "lastChecked": "2022-04-28T00:00:00Z",
        "format": "hd",
        "mbps": "3795",
        "URI": [
            "s"
        ]
    },
    {
        "id": "2512461",
        "channel": "HBO SIGNATURE",
        "link": "https://list.iptvcat.com/my_list/s/5f317df9a2331fface52b31895b269bc.m3u8",
        "country": "brazil",
        "liveliness": "86",
        "status": "offline",
        "lastChecked": "2022-04-28T00:00:00Z",
        "format": "fhd 2k",
        "mbps": "13324",
        "URI": [
            "s"
        ]
    },
    {
        "id": "2512640",
        "channel": "HBO SIGNATURE",
        "link": "https://list.iptvcat.com/my_list/s/0836c01cd0d441e062ff3882deee4310.m3u8",
        "country": "brazil",
        "liveliness": "91",
        "status": "offline",
        "lastChecked": "2022-04-28T00:00:00Z",
        "format": "fhd 2k",
        "mbps": "13324",
        "URI": [
            "s"
        ]
    },
    {
        "id": "2485039",
        "channel": "HBO Signature HD",
        "link": "https://list.iptvcat.com/my_list/s/65a270a9ec8318c61a253355b7aa5eae.m3u8",
        "country": "brazil",
        "liveliness": "96",
        "status": "online",
        "lastChecked": "2022-04-28T00:00:00Z",
        "format": "hd",
        "mbps": "5991",
        "URI": [
            "s"
        ]
    },
    {
        "id": "2511495",
        "channel": "Hallmark Channel",
        "link": "https://list.iptvcat.com/my_list/s/163fcd69ada93aad521ab673a3fffa4a.m3u8",
        "country": "brazil",
        "liveliness": "39",
        "status": "offline",
        "lastChecked": "2022-04-28T00:00:00Z",
        "format": "fhd 2k",
        "mbps": "13311",
        "URI": [
            "s"
        ]
    },
    {
        "id": "2512644",
        "channel": "LIFETIME",
        "link": "https://list.iptvcat.com/my_list/s/37a2844318c14d6b6dcd12380b5c4ee9.m3u8",
        "country": "brazil",
        "liveliness": "91",
        "status": "offline",
        "lastChecked": "2022-04-28T00:00:00Z",
        "format": "hd",
        "mbps": "5997",
        "URI": [
            "s"
        ]
    },
    {
        "id": "2512464",
        "channel": "LIFETIME",
        "link": "https://list.iptvcat.com/my_list/s/3ec31b9fdd841ee2f6d0e2f3c3c35d3e.m3u8",
        "country": "brazil",
        "liveliness": "43",
        "status": "offline",
        "lastChecked": "2022-04-28T00:00:00Z",
        "format": "hd",
        "mbps": "3795",
        "URI": [
            "s"
        ]
    },
    {
        "id": "2485773",
        "channel": "Lifetime FHD",
        "link": "https://list.iptvcat.com/my_list/s/d889d71255881785631a071a3dd0fdd5.m3u8",
        "country": "brazil",
        "liveliness": "97",
        "status": "online",
        "lastChecked": "2022-04-28T00:00:00Z",
        "format": "hd",
        "mbps": "3795",
        "URI": [
            "s"
        ]
    },
    {
        "id": "2484537",
        "channel": "Cinemax HD",
        "link": "https://list.iptvcat.com/my_list/s/28a4b5ad9e4673cc11471baa8e20bc3a.m3u8",
        "country": "brazil",
        "liveliness": "96",
        "status": "online",
        "lastChecked": "2022-04-28T00:00:00Z",
        "format": "fhd 2k",
        "mbps": "13324",
        "URI": [
            "s"
        ]
    },
    {
        "id": "2512644",
        "channel": "LIFETIME",
        "link": "https://list.iptvcat.com/my_list/s/37a2844318c14d6b6dcd12380b5c4ee9.m3u8",
        "country": "brazil",
        "liveliness": "91",
        "status": "offline",
        "lastChecked": "2022-04-28T00:00:00Z",
        "format": "hd",
        "mbps": "5997",
        "URI": [
            "s"
        ]
    },
    {
        "id": "2512464",
        "channel": "LIFETIME",
        "link": "https://list.iptvcat.com/my_list/s/3ec31b9fdd841ee2f6d0e2f3c3c35d3e.m3u8",
        "country": "brazil",
        "liveliness": "43",
        "status": "offline",
        "lastChecked": "2022-04-28T00:00:00Z",
        "format": "hd",
        "mbps": "3795",
        "URI": [
            "s"
        ]
    },
    {
        "id": "2485773",
        "channel": "Lifetime FHD",
        "link": "https://list.iptvcat.com/my_list/s/d889d71255881785631a071a3dd0fdd5.m3u8",
        "country": "brazil",
        "liveliness": "97",
        "status": "online",
        "lastChecked": "2022-04-28T00:00:00Z",
        "format": "hd",
        "mbps": "3795",
        "URI": [
            "s"
        ]
    },
    {
        "id": "2512618",
        "channel": "DISNEY CHANNEL",
        "link": "https://list.iptvcat.com/my_list/s/34fae9b81bf296311fde7bcc395ba523.m3u8",
        "country": "brazil",
        "liveliness": "90",
        "status": "offline",
        "lastChecked": "2022-04-28T00:00:00Z",
        "format": "hd",
        "mbps": "5991",
        "URI": [
            "s"
        ]
    },
    {
        "id": "2512415",
        "channel": "DISNEY CHANNEL",
        "link": "https://list.iptvcat.com/my_list/s/24ede2fe6f37fd4fdf73a0075bba201e.m3u8",
        "country": "brazil",
        "liveliness": "56",
        "status": "offline",
        "lastChecked": "2022-04-28T00:00:00Z",
        "format": "hd",
        "mbps": "3795",
        "URI": [
            "s"
        ]
    },
    {
        "id": "2512619",
        "channel": "DISNEY JR",
        "link": "https://list.iptvcat.com/my_list/s/ff92da3d5d84c8ec34af224263d82a30.m3u8",
        "country": "brazil",
        "liveliness": "78",
        "status": "offline",
        "lastChecked": "2022-04-28T00:00:00Z",
        "format": "hd",
        "mbps": "3799",
        "URI": [
            "s"
        ]
    },
    {
        "id": "2484648",
        "channel": "Disney Channel HD",
        "link": "https://list.iptvcat.com/my_list/s/eebef84ee650d8bc65f30f81b8e00c55.m3u8",
        "country": "brazil",
        "liveliness": "99",
        "status": "online",
        "lastChecked": "2022-04-28T00:00:00Z",
        "format": "hd",
        "mbps": "5991",
        "URI": [
            "s"
        ]
    },
    {
        "id": "2511081",
        "channel": "Disney Junior HD",
        "link": "https://list.iptvcat.com/my_list/s/e5b23a5d409360653a7e07b23c1069a5.m3u8",
        "country": "brazil",
        "liveliness": "36",
        "status": "offline",
        "lastChecked": "2022-04-28T00:00:00Z",
        "format": "hd",
        "mbps": "5991",
        "URI": [
            "s"
        ]
    },
    {
        "id": "2484655",
        "channel": "Disney Junior HD",
        "link": "https://list.iptvcat.com/my_list/s/339f9cb82ef922acbe12c4c59a4378bf.m3u8",
        "country": "brazil",
        "liveliness": "98",
        "status": "online",
        "lastChecked": "2022-04-28T00:00:00Z",
        "format": "sd",
        "mbps": "1681",
        "URI": [
            "s"
        ]
    },
    {
        "id": "2511082",
        "channel": "Disney XD HD",
        "link": "https://list.iptvcat.com/my_list/s/a8978d456e53cf92d1a831ebae6842a1.m3u8",
        "country": "brazil",
        "liveliness": "63",
        "status": "offline",
        "lastChecked": "2022-04-28T00:00:00Z",
        "format": "hd",
        "mbps": "5991",
        "URI": [
            "s"
        ]
    },
    {
        "id": "2485180",
        "channel": "Disney XD HD",
        "link": "https://list.iptvcat.com/my_list/s/cfb438d65145482d68f0644a24eefb75.m3u8",
        "country": "brazil",
        "liveliness": "97",
        "status": "online",
        "lastChecked": "2022-04-28T00:00:00Z",
        "format": "fhd 2k",
        "mbps": "13324",
        "URI": [
            "s"
        ]
    }
]