[
    {
        "id": "2458091",
        "channel": "MOVIETIME",
        "link": "https://list.iptvcat.com/my_list/s/7de08cb10b1a244d5cdf3dcfd9b21b99.m3u8",
        "country": "canada",
        "liveliness": "74",
        "status": "offline",
        "lastChecked": "2022-03-29T00:00:00Z",
        "format": "hd",
        "mbps": "3795",
        "URI": [
            "s"
        ]
    },
    {
        "id": "2465397",
        "channel": "MovieTime",
        "link": "https://list.iptvcat.com/my_list/s/6d9b055c4534a251ce20d6f2310f0fde.m3u8",
        "country": "canada",
        "liveliness": "10",
        "status": "offline",
        "lastChecked": "2022-03-29T00:00:00Z",
        "format": "hd",
        "mbps": "3795",
        "URI": [
            "s"
        ]
    },
    {
        "id": "2465435",
        "channel": "Turner Classic Movies",
        "link": "https://list.iptvcat.com/my_list/s/0fd78aca66f6c34d5cf8c69b7261efd9.m3u8",
        "country": "canada",
        "liveliness": "20",
        "status": "offline",
        "lastChecked": "2022-03-29T00:00:00Z",
        "format": "hd",
        "mbps": "3795",
        "URI": [
            "s"
        ]
    },
    {
        "id": "2458007",
        "channel": "DAYSTAR",
        "link": "https://list.iptvcat.com/my_list/s/fc303098d4002568faaa0533cadbe430.m3u8",
        "country": "canada",
        "liveliness": "75",
        "status": "offline",
        "lastChecked": "2022-03-29T00:00:00Z",
        "format": "hd",
        "mbps": "3795",
        "URI": [
            "s"
        ]
    },
    {
        "id": "2449444",
        "channel": "Daystar",
        "link": "https://list.iptvcat.com/my_list/s/7f9a2a6ecf9f5fd9e5b2606efd1bca94.m3u8",
        "country": "canada",
        "liveliness": "97",
        "status": "online",
        "lastChecked": "2022-03-29T00:00:00Z",
        "format": "hd",
        "mbps": "3795",
        "URI": [
            "s"
        ]
    },
    {
        "id": "2465171",
        "channel": "Daystar TV",
        "link": "https://list.iptvcat.com/my_list/s/d93c2a9bab80b87b20743e0db3c7da6f.m3u8",
        "country": "canada",
        "liveliness": "10",
        "status": "offline",
        "lastChecked": "2022-03-29T00:00:00Z",
        "format": "sd",
        "mbps": "3883",
        "URI": [
            "s"
        ]
    },
    {
        "id": "2459510",
        "channel": "ENC1E (STARZ 1)",
        "link": "https://list.iptvcat.com/my_list/s/247c739ff2e6b23b64d3290e4aa2ef85.m3u8",
        "country": "canada",
        "liveliness": "47",
        "status": "offline",
        "lastChecked": "2022-03-29T00:00:00Z",
        "format": "sd",
        "mbps": "3883",
        "URI": [
            "s"
        ]
    },
    {
        "id": "2450780",
        "channel": "Starz 1",
        "link": "https://list.iptvcat.com/my_list/s/778df9a23e842046f8cacac4f1ed7047.m3u8",
        "country": "canada",
        "liveliness": "85",
        "status": "online",
        "lastChecked": "2022-03-29T00:00:00Z",
        "format": "hd",
        "mbps": "3795",
        "URI": [
            "s"
        ]
    },
    {
        "id": "2450799",
        "channel": "Starz 2",
        "link": "https://list.iptvcat.com/my_list/s/88a0d5bb951d6991557282baad5305cb.m3u8",
        "country": "canada",
        "liveliness": "90",
        "status": "online",
        "lastChecked": "2022-03-29T00:00:00Z",
        "format": "hd",
        "mbps": "3795",
        "URI": [
            "s"
        ]
    },
    {
        "id": "2458081",
        "channel": "LIFETIME",
        "link": "https://list.iptvcat.com/my_list/s/9703b370c4ef3a66ee4167476dd5f4b9.m3u8",
        "country": "canada",
        "liveliness": "68",
        "status": "offline",
        "lastChecked": "2022-03-29T00:00:00Z",
        "format": "hd",
        "mbps": "3795",
        "URI": [
            "s"
        ]
    },
    {
        "id": "2450018",
        "channel": "Lifetime",
        "link": "https://list.iptvcat.com/my_list/s/b87bfd33f10ec39d649b18e9a5e3bed8.m3u8",
        "country": "canada",
        "liveliness": "79",
        "status": "online",
        "lastChecked": "2022-03-29T00:00:00Z",
        "format": "hd",
        "mbps": "3795",
        "URI": [
            "s"
        ]
    },
    {
        "id": "2458081",
        "channel": "LIFETIME",
        "link": "https://list.iptvcat.com/my_list/s/9703b370c4ef3a66ee4167476dd5f4b9.m3u8",
        "country": "canada",
        "liveliness": "68",
        "status": "offline",
        "lastChecked": "2022-03-29T00:00:00Z",
        "format": "hd",
        "mbps": "3795",
        "URI": [
            "s"
        ]
    },
    {
        "id": "2450018",
        "channel": "Lifetime",
        "link": "https://list.iptvcat.com/my_list/s/b87bfd33f10ec39d649b18e9a5e3bed8.m3u8",
        "country": "canada",
        "liveliness": "79",
        "status": "online",
        "lastChecked": "2022-03-29T00:00:00Z",
        "format": "hd",
        "mbps": "3795",
        "URI": [
            "s"
        ]
    },
    {
        "id": "2458011",
        "channel": "DISNEY",
        "link": "https://list.iptvcat.com/my_list/s/c0db4bd6239b2ae52a4e9cec83ebbc18.m3u8",
        "country": "canada",
        "liveliness": "77",
        "status": "offline",
        "lastChecked": "2022-03-29T00:00:00Z",
        "format": "hd",
        "mbps": "3795",
        "URI": [
            "s"
        ]
    },
    {
        "id": "2458012",
        "channel": "DISNEY CHANNEL",
        "link": "https://list.iptvcat.com/my_list/s/36193a52049ff20e3b67fb004979d8f0.m3u8",
        "country": "canada",
        "liveliness": "76",
        "status": "offline",
        "lastChecked": "2022-03-29T00:00:00Z",
        "format": "hd",
        "mbps": "3795",
        "URI": [
            "s"
        ]
    },
    {
        "id": "2459513",
        "channel": "DISNEY FRENCH",
        "link": "https://list.iptvcat.com/my_list/s/40a09a16ee8a600482c2508ae49c5c58.m3u8",
        "country": "canada",
        "liveliness": "38",
        "status": "offline",
        "lastChecked": "2022-03-29T00:00:00Z",
        "format": "sd",
        "mbps": "3883",
        "URI": [
            "s"
        ]
    },
    {
        "id": "2458013",
        "channel": "DISNEY JR",
        "link": "https://list.iptvcat.com/my_list/s/69401674315e1c37599e5d4f89c19e97.m3u8",
        "country": "canada",
        "liveliness": "76",
        "status": "offline",
        "lastChecked": "2022-03-29T00:00:00Z",
        "format": "hd",
        "mbps": "3795",
        "URI": [
            "s"
        ]
    },
    {
        "id": "2458015",
        "channel": "DISNEY XD",
        "link": "https://list.iptvcat.com/my_list/s/e2435bcf799baf2e40f2b9bb6702ee64.m3u8",
        "country": "canada",
        "liveliness": "76",
        "status": "offline",
        "lastChecked": "2022-03-29T00:00:00Z",
        "format": "hd",
        "mbps": "3795",
        "URI": [
            "s"
        ]
    },
    {
        "id": "2458016",
        "channel": "DISNEY, LA CHAINE",
        "link": "https://list.iptvcat.com/my_list/s/c37a71f649843456d750eb12afbd5e74.m3u8",
        "country": "canada",
        "liveliness": "75",
        "status": "offline",
        "lastChecked": "2022-03-29T00:00:00Z",
        "format": "hd",
        "mbps": "3795",
        "URI": [
            "s"
        ]
    },
    {
        "id": "2449492",
        "channel": "Disney Channel",
        "link": "https://list.iptvcat.com/my_list/s/8b2e6ef1279c4e17c762dd65944e33a4.m3u8",
        "country": "canada",
        "liveliness": "77",
        "status": "online",
        "lastChecked": "2022-03-29T00:00:00Z",
        "format": "hd",
        "mbps": "3795",
        "URI": [
            "s"
        ]
    },
    {
        "id": "2451927",
        "channel": "Disney Channel HD",
        "link": "https://list.iptvcat.com/my_list/s/77a655a9453be52fba489f5cf3472e85.m3u8",
        "country": "canada",
        "liveliness": "46",
        "status": "offline",
        "lastChecked": "2022-03-29T00:00:00Z",
        "format": "hd",
        "mbps": "3795",
        "URI": [
            "s"
        ]
    },
    {
        "id": "2465487",
        "channel": "Disney Channel HD",
        "link": "https://list.iptvcat.com/my_list/s/0287ea267bf8a3cef1b1434fe8b24c9d.m3u8",
        "country": "canada",
        "liveliness": "20",
        "status": "offline",
        "lastChecked": "2022-03-29T00:00:00Z",
        "format": "hd",
        "mbps": "3795",
        "URI": [
            "s"
        ]
    },
    {
        "id": "2451929",
        "channel": "Disney Junior",
        "link": "https://list.iptvcat.com/my_list/s/210ae8733bf8c9332ccc24419220cf46.m3u8",
        "country": "canada",
        "liveliness": "38",
        "status": "offline",
        "lastChecked": "2022-03-29T00:00:00Z",
        "format": "hd",
        "mbps": "3795",
        "URI": [
            "s"
        ]
    },
    {
        "id": "2465488",
        "channel": "Disney Junior HD",
        "link": "https://list.iptvcat.com/my_list/s/748f65ae21f01e516b95e54aac323f50.m3u8",
        "country": "canada",
        "liveliness": "20",
        "status": "offline",
        "lastChecked": "2022-03-29T00:00:00Z",
        "format": "hd",
        "mbps": "3795",
        "URI": [
            "s"
        ]
    },
    {
        "id": "2449494",
        "channel": "Disney XD",
        "link": "https://list.iptvcat.com/my_list/s/88737b87d1a00ceb2a283729b1ea79df.m3u8",
        "country": "canada",
        "liveliness": "90",
        "status": "online",
        "lastChecked": "2022-03-29T00:00:00Z",
        "format": "hd",
        "mbps": "3795",
        "URI": [
            "s"
        ]
    },
    {
        "id": "2465489",
        "channel": "Disney XD HD",
        "link": "https://list.iptvcat.com/my_list/s/6cf91310660c546d1d09613ea5d54674.m3u8",
        "country": "canada",
        "liveliness": "20",
        "status": "offline",
        "lastChecked": "2022-03-29T00:00:00Z",
        "format": "hd",
        "mbps": "3795",
        "URI": [
            "s"
        ]
    }
]