[
    {
        "id": "2671813",
        "channel": "Blue Sky",
        "link": "https://list.iptvcat.com/my_list/s/2b7b6bb4a733dae99d31c299707b80fe.m3u8",
        "country": "greece",
        "liveliness": "83",
        "status": "offline",
        "lastChecked": "2023-02-19T00:00:00Z",
        "format": "sd",
        "mbps": "2089",
        "URI": [
            "s"
        ]
    },
    {
        "id": "2672272",
        "channel": "Nova Premiere Starz",
        "link": "https://list.iptvcat.com/my_list/s/447bd5601e31be60b6a9124cd2ace26e.m3u8",
        "country": "greece",
        "liveliness": "78",
        "status": "offline",
        "lastChecked": "2023-02-19T00:00:00Z",
        "format": "fhd 2k",
        "mbps": "6724",
        "URI": [
            "s"
        ]
    },
    {
        "id": "2672327",
        "channel": "Nova Sports Start",
        "link": "https://list.iptvcat.com/my_list/s/d40558acb986494290504ec31c1615e8.m3u8",
        "country": "greece",
        "liveliness": "79",
        "status": "online",
        "lastChecked": "2023-02-19T00:00:00Z",
        "format": "fhd 2k",
        "mbps": "22116",
        "URI": [
            "s"
        ]
    },
    {
        "id": "2659808",
        "channel": "STAR HD",
        "link": "https://list.iptvcat.com/my_list/s/15749f93721eb5d89d946d65e261e9b0.m3u8",
        "country": "greece",
        "liveliness": "100",
        "status": "online",
        "lastChecked": "2023-02-19T00:00:00Z",
        "format": "hd",
        "mbps": "5020",
        "URI": [
            "s"
        ]
    },
    {
        "id": "2593049",
        "channel": "Star",
        "link": "https://list.iptvcat.com/my_list/s/8168cefd9a147c10bda353bd4bff4b5f.m3u8",
        "country": "greece",
        "liveliness": "100",
        "status": "online",
        "lastChecked": "2023-02-19T00:00:00Z",
        "format": "fhd 2k",
        "mbps": "7004",
        "URI": [
            "s"
        ]
    },
    {
        "id": "2672360",
        "channel": "Star Channel",
        "link": "https://list.iptvcat.com/my_list/s/71e52f12e77bc979a2b6ab6eb0fbc521.m3u8",
        "country": "greece",
        "liveliness": "81",
        "status": "online",
        "lastChecked": "2023-02-19T00:00:00Z",
        "format": "hd",
        "mbps": "5020",
        "URI": [
            "s"
        ]
    },
    {
        "id": "2672363",
        "channel": "Star Kentrikis",
        "link": "https://list.iptvcat.com/my_list/s/668ab2aaa375973f911a40669601a52f.m3u8",
        "country": "greece",
        "liveliness": "74",
        "status": "online",
        "lastChecked": "2023-02-19T00:00:00Z",
        "format": "sd",
        "mbps": "1677",
        "URI": [
            "s"
        ]
    },
    {
        "id": "2672365",
        "channel": "Start TV",
        "link": "https://list.iptvcat.com/my_list/s/e80b3e4258bb5331843ccb4d5a3b81fc.m3u8",
        "country": "greece",
        "liveliness": "81",
        "status": "online",
        "lastChecked": "2023-02-19T00:00:00Z",
        "format": "sd",
        "mbps": "1688",
        "URI": [
            "s"
        ]
    },
    {
        "id": "2672066",
        "channel": "HBO",
        "link": "https://list.iptvcat.com/my_list/s/88a3f64fa2e240ca5ef962a1f88bf88a.m3u8",
        "country": "greece",
        "liveliness": "63",
        "status": "online",
        "lastChecked": "2023-02-19T00:00:00Z",
        "format": "fhd 2k",
        "mbps": "7004",
        "URI": [
            "s"
        ]
    },
    {
        "id": "2671853",
        "channel": "COSMOTE CINEMA 1",
        "link": "https://list.iptvcat.com/my_list/s/7dc12a42049b40e6927245341c931de5.m3u8",
        "country": "greece",
        "liveliness": "57",
        "status": "offline",
        "lastChecked": "2023-02-19T00:00:00Z",
        "format": "hd",
        "mbps": "5020",
        "URI": [
            "s"
        ]
    },
    {
        "id": "2671856",
        "channel": "COSMOTE CINEMA 2",
        "link": "https://list.iptvcat.com/my_list/s/11a91b94080857953076fd11b7c9433e.m3u8",
        "country": "greece",
        "liveliness": "76",
        "status": "online",
        "lastChecked": "2023-02-19T00:00:00Z",
        "format": "hd",
        "mbps": "7114",
        "URI": [
            "s"
        ]
    },
    {
        "id": "2671825",
        "channel": "Cinemax",
        "link": "https://list.iptvcat.com/my_list/s/da51a3d06c9e18f3bd128e77769173e5.m3u8",
        "country": "greece",
        "liveliness": "85",
        "status": "online",
        "lastChecked": "2023-02-19T00:00:00Z",
        "format": "hd",
        "mbps": "3625",
        "URI": [
            "s"
        ]
    },
    {
        "id": "2671827",
        "channel": "Cinemax 2",
        "link": "https://list.iptvcat.com/my_list/s/cc206f054114ebabe554237216521133.m3u8",
        "country": "greece",
        "liveliness": "77",
        "status": "online",
        "lastChecked": "2023-02-19T00:00:00Z",
        "format": "fhd 2k",
        "mbps": "7004",
        "URI": [
            "s"
        ]
    },
    {
        "id": "2672192",
        "channel": "Nova Cinema 1",
        "link": "https://list.iptvcat.com/my_list/s/56ea33473d4c5648535d7f77e09a513b.m3u8",
        "country": "greece",
        "liveliness": "76",
        "status": "online",
        "lastChecked": "2023-02-19T00:00:00Z",
        "format": "hd",
        "mbps": "5020",
        "URI": [
            "s"
        ]
    },
    {
        "id": "2672195",
        "channel": "Nova Cinema 2",
        "link": "https://list.iptvcat.com/my_list/s/3588792efb6a1305f74f8db94197b2b8.m3u8",
        "country": "greece",
        "liveliness": "80",
        "status": "online",
        "lastChecked": "2023-02-19T00:00:00Z",
        "format": "sd",
        "mbps": "6311",
        "URI": [
            "s"
        ]
    },
    {
        "id": "2672197",
        "channel": "Nova Cinema 3",
        "link": "https://list.iptvcat.com/my_list/s/ad8e5e437d5c567048c38b7e5b5f6740.m3u8",
        "country": "greece",
        "liveliness": "75",
        "status": "online",
        "lastChecked": "2023-02-19T00:00:00Z",
        "format": "fhd 2k",
        "mbps": "22116",
        "URI": [
            "s"
        ]
    },
    {
        "id": "2672209",
        "channel": "Nova Cinema 4",
        "link": "https://list.iptvcat.com/my_list/s/131375096931985ccf97ca77be3887c2.m3u8",
        "country": "greece",
        "liveliness": "84",
        "status": "online",
        "lastChecked": "2023-02-19T00:00:00Z",
        "format": "sd",
        "mbps": "5020",
        "URI": [
            "s"
        ]
    }
]