[
    {
        "id": "2659869",
        "channel": "Rakuten Action Movies",
        "link": "https://list.iptvcat.com/my_list/s/b60d709c766730ac4f4f79a9f566fec5.m3u8",
        "country": "ireland",
        "liveliness": "83",
        "status": "offline",
        "lastChecked": "2022-12-01T00:00:00Z",
        "format": "hd",
        "mbps": "4821, ...",
        "URI": [
            "s"
        ]
    },
    {
        "id": "2659870",
        "channel": "Rakuten Comedy Movies",
        "link": "https://list.iptvcat.com/my_list/s/173feb93dabb3bfcda7a7c98441efec7.m3u8",
        "country": "ireland",
        "liveliness": "84",
        "status": "offline",
        "lastChecked": "2022-12-01T00:00:00Z",
        "format": "hd",
        "mbps": "4821, ...",
        "URI": [
            "s"
        ]
    }
]