[
    {
        "id": "2540886",
        "channel": "IT Rai Movie",
        "link": "https://list.iptvcat.com/my_list/s/3ca1ecec9c438b908c8c6603c8997786.m3u8",
        "country": "italy",
        "liveliness": "67",
        "status": "online",
        "lastChecked": "2022-05-09T00:00:00Z",
        "format": "fhd 2k",
        "mbps": "7004",
        "URI": [
            "s"
        ]
    },
    {
        "id": "2540685",
        "channel": "IT Rai_Movie",
        "link": "https://list.iptvcat.com/my_list/s/a136aa8942ac84081ab225eda7cebf23.m3u8",
        "country": "italy",
        "liveliness": "100",
        "status": "online",
        "lastChecked": "2022-05-09T00:00:00Z",
        "format": "fhd 2k",
        "mbps": "7004",
        "URI": [
            "s"
        ]
    },
    {
        "id": "2540679",
        "channel": "IT Rai_Movie_HD",
        "link": "https://list.iptvcat.com/my_list/s/8dcd6406dfc6e488914d507ea8549212.m3u8",
        "country": "italy",
        "liveliness": "100",
        "status": "online",
        "lastChecked": "2022-05-09T00:00:00Z",
        "format": "fhd 2k",
        "mbps": "7004",
        "URI": [
            "s"
        ]
    },
    {
        "id": "2543611",
        "channel": "IT_RAI_Movie",
        "link": "https://list.iptvcat.com/my_list/s/85d5654dcbed6f10f70c265a266d8ae8.m3u8",
        "country": "italy",
        "liveliness": "100",
        "status": "online",
        "lastChecked": "2022-05-09T00:00:00Z",
        "format": "fhd 2k",
        "mbps": "7004",
        "URI": [
            "s"
        ]
    },
    {
        "id": "2537045",
        "channel": "Rai Movie",
        "link": "https://list.iptvcat.com/my_list/s/152580003717ca4c6b238fa833fcc1e1.m3u8",
        "country": "italy",
        "liveliness": "62",
        "status": "offline",
        "lastChecked": "2022-05-09T00:00:00Z",
        "format": "hd",
        "mbps": "3188",
        "URI": [
            "s"
        ]
    },
    {
        "id": "2536871",
        "channel": "Rai Movie FHD",
        "link": "https://list.iptvcat.com/my_list/s/38db83ebf83790fc0d2dc9070b82d1dd.m3u8",
        "country": "italy",
        "liveliness": "27",
        "status": "offline",
        "lastChecked": "2022-05-09T00:00:00Z",
        "format": "hd",
        "mbps": "5020",
        "URI": [
            "s"
        ]
    },
    {
        "id": "2287427",
        "channel": "Rai Movie FHD",
        "link": "https://list.iptvcat.com/my_list/s/e14edb2453d923a8e9b9726ace1981bc.m3u8",
        "country": "italy",
        "liveliness": "58",
        "status": "online",
        "lastChecked": "2022-05-09T00:00:00Z",
        "format": "hd",
        "mbps": "5020",
        "URI": [
            "s"
        ]
    },
    {
        "id": "2538013",
        "channel": "Rai Movie FHD",
        "link": "https://list.iptvcat.com/my_list/s/5125613ee216a27729ad62031cbc8737.m3u8",
        "country": "italy",
        "liveliness": "100",
        "status": "online",
        "lastChecked": "2022-05-09T00:00:00Z",
        "format": "hd",
        "mbps": "5020",
        "URI": [
            "s"
        ]
    },
    {
        "id": "2538651",
        "channel": "Rai Movie FHD",
        "link": "https://list.iptvcat.com/my_list/s/61211dd2ebe280ba9df461dadfc0328a.m3u8",
        "country": "italy",
        "liveliness": "100",
        "status": "online",
        "lastChecked": "2022-05-09T00:00:00Z",
        "format": "hd",
        "mbps": "5020",
        "URI": [
            "s"
        ]
    },
    {
        "id": "2536864",
        "channel": "Rai Movie HD",
        "link": "https://list.iptvcat.com/my_list/s/8682d3f7cae86ba1989b62546da6a632.m3u8",
        "country": "italy",
        "liveliness": "18",
        "status": "offline",
        "lastChecked": "2022-05-09T00:00:00Z",
        "format": "hd",
        "mbps": "5020",
        "URI": [
            "s"
        ]
    },
    {
        "id": "2484620",
        "channel": "Rai Movie HD",
        "link": "https://list.iptvcat.com/my_list/s/bb829efad29440f46b911beb11c55bc6.m3u8",
        "country": "italy",
        "liveliness": "93",
        "status": "online",
        "lastChecked": "2022-05-09T00:00:00Z",
        "format": "hd",
        "mbps": "5020",
        "URI": [
            "s"
        ]
    },
    {
        "id": "2538655",
        "channel": "Rai Movie HD",
        "link": "https://list.iptvcat.com/my_list/s/675736f269d684868e51097964a4bc7a.m3u8",
        "country": "italy",
        "liveliness": "100",
        "status": "online",
        "lastChecked": "2022-05-09T00:00:00Z",
        "format": "hd",
        "mbps": "5020",
        "URI": [
            "s"
        ]
    },
    {
        "id": "2538014",
        "channel": "Rai Movie HD",
        "link": "https://list.iptvcat.com/my_list/s/069976fca87ef02636238659f1650d99.m3u8",
        "country": "italy",
        "liveliness": "100",
        "status": "online",
        "lastChecked": "2022-05-09T00:00:00Z",
        "format": "hd",
        "mbps": "5020",
        "URI": [
            "s"
        ]
    },
    {
        "id": "2526842",
        "channel": "Rai Movie HD+",
        "link": "https://list.iptvcat.com/my_list/s/df071819778a71c82f843a7851c87b91.m3u8",
        "country": "italy",
        "liveliness": "42",
        "status": "offline",
        "lastChecked": "2022-05-09T00:00:00Z",
        "format": "fhd 2k",
        "mbps": "7004",
        "URI": [
            "s"
        ]
    },
    {
        "id": "2521561",
        "channel": "VIP Rai Movie FHD",
        "link": "https://list.iptvcat.com/my_list/s/7a75adf2a48d581ee213c12f3af558cf.m3u8",
        "country": "italy",
        "liveliness": "59",
        "status": "offline",
        "lastChecked": "2022-05-09T00:00:00Z",
        "format": "fhd 2k",
        "mbps": "7004",
        "URI": [
            "s"
        ]
    },
    {
        "id": "2520843",
        "channel": "VIP Rai Movie FHD",
        "link": "https://list.iptvcat.com/my_list/s/e5d3c3ff36c5d1f11908ad2ec9d62ca7.m3u8",
        "country": "italy",
        "liveliness": "54",
        "status": "offline",
        "lastChecked": "2022-05-09T00:00:00Z",
        "format": "fhd 2k",
        "mbps": "7004",
        "URI": [
            "s"
        ]
    },
    {
        "id": "2520844",
        "channel": "VIP Rai Movie HD",
        "link": "https://list.iptvcat.com/my_list/s/0df5d21c9749fb27e2e2b545d7e7d99d.m3u8",
        "country": "italy",
        "liveliness": "49",
        "status": "offline",
        "lastChecked": "2022-05-09T00:00:00Z",
        "format": "sd",
        "mbps": "3262",
        "URI": [
            "s"
        ]
    },
    {
        "id": "2521562",
        "channel": "VIP Rai Movie HD",
        "link": "https://list.iptvcat.com/my_list/s/a3ec69ae5a5930f57fae2cedd784e745.m3u8",
        "country": "italy",
        "liveliness": "50",
        "status": "offline",
        "lastChecked": "2022-05-09T00:00:00Z",
        "format": "fhd 2k",
        "mbps": "7004",
        "URI": [
            "s"
        ]
    },
    {
        "id": "2536817",
        "channel": "Disney HD",
        "link": "https://list.iptvcat.com/my_list/s/06f399d5f084c3b0c4e617ee50521982.m3u8",
        "country": "italy",
        "liveliness": "9",
        "status": "offline",
        "lastChecked": "2022-05-09T00:00:00Z",
        "format": "sd",
        "mbps": "2334",
        "URI": [
            "s"
        ]
    },
    {
        "id": "2536826",
        "channel": "Disney Junior",
        "link": "https://list.iptvcat.com/my_list/s/79347bc9704ea90a48917b08880001d6.m3u8",
        "country": "italy",
        "liveliness": "9",
        "status": "offline",
        "lastChecked": "2022-05-09T00:00:00Z",
        "format": "sd",
        "mbps": "2334",
        "URI": [
            "s"
        ]
    }
]