[
    {
        "id": "2614047",
        "channel": "Az Cinema",
        "link": "https://list.iptvcat.com/my_list/s/d131de4501bbd1d4a95378ab1aa54fb3.m3u8",
        "country": "mexico",
        "liveliness": "57",
        "status": "offline",
        "lastChecked": "2022-09-14T00:00:00Z",
        "format": "sd",
        "mbps": "2480",
        "URI": [
            "s"
        ]
    },
    {
        "id": "2609228",
        "channel": "Cinemax HD",
        "link": "https://list.iptvcat.com/my_list/s/79901ae954ead147568441c8f42b7d80.m3u8",
        "country": "mexico",
        "liveliness": "25",
        "status": "offline",
        "lastChecked": "2022-09-14T00:00:00Z",
        "format": "fhd 2k",
        "mbps": "13311",
        "URI": [
            "s"
        ]
    },
    {
        "id": "2614081",
        "channel": "Claro Cinema",
        "link": "https://list.iptvcat.com/my_list/s/b0cb8287fa902ab1f0a1e0aa4c20a91a.m3u8",
        "country": "mexico",
        "liveliness": "71",
        "status": "online",
        "lastChecked": "2022-09-14T00:00:00Z",
        "format": "sd",
        "mbps": "1795",
        "URI": [
            "s"
        ]
    },
    {
        "id": "2614104",
        "channel": "Disney Junior",
        "link": "https://list.iptvcat.com/my_list/s/6a77e663abb5539ff47565e5e11e70d7.m3u8",
        "country": "mexico",
        "liveliness": "71",
        "status": "offline",
        "lastChecked": "2022-09-14T00:00:00Z",
        "format": "hd",
        "mbps": "5991",
        "URI": [
            "s"
        ]
    }
]