[
    {
        "id": "2557389",
        "channel": "VIP HBO 1 HD",
        "link": "https://list.iptvcat.com/my_list/s/b731eb17fbe8705b393d3847ab3f8ade.m3u8",
        "country": "netherlands",
        "liveliness": "96",
        "status": "online",
        "lastChecked": "2022-07-11T00:00:00Z",
        "format": "fhd 2k",
        "mbps": "7004",
        "URI": [
            "s"
        ]
    },
    {
        "id": "2557390",
        "channel": "VIP HBO 2 HD",
        "link": "https://list.iptvcat.com/my_list/s/b826f590e13d133fb6d8e617947f348c.m3u8",
        "country": "netherlands",
        "liveliness": "99",
        "status": "online",
        "lastChecked": "2022-07-11T00:00:00Z",
        "format": "fhd 2k",
        "mbps": "7004",
        "URI": [
            "s"
        ]
    },
    {
        "id": "2557391",
        "channel": "VIP HBO 3 HD",
        "link": "https://list.iptvcat.com/my_list/s/52af57d7a9fce5a201794fb850b11b16.m3u8",
        "country": "netherlands",
        "liveliness": "96",
        "status": "online",
        "lastChecked": "2022-07-11T00:00:00Z",
        "format": "fhd 2k",
        "mbps": "7004",
        "URI": [
            "s"
        ]
    },
    {
        "id": "2489974",
        "channel": "DISNEY CHANNEL",
        "link": "https://list.iptvcat.com/my_list/s/cb77fa21ad64a0efc4b90e190b6969df.m3u8",
        "country": "netherlands",
        "liveliness": "99",
        "status": "online",
        "lastChecked": "2022-07-11T00:00:00Z",
        "format": "sd",
        "mbps": "1736",
        "URI": [
            "s"
        ]
    },
    {
        "id": "2489978",
        "channel": "DISNEY JUNIOR",
        "link": "https://list.iptvcat.com/my_list/s/89df2186eecc5f1401087ac89900a29c.m3u8",
        "country": "netherlands",
        "liveliness": "99",
        "status": "online",
        "lastChecked": "2022-07-11T00:00:00Z",
        "format": "sd",
        "mbps": "1736",
        "URI": [
            "s"
        ]
    },
    {
        "id": "2557403",
        "channel": "DISNEY XD",
        "link": "https://list.iptvcat.com/my_list/s/6868810a89839cd19dad1bfc17b3ec61.m3u8",
        "country": "netherlands",
        "liveliness": "98",
        "status": "online",
        "lastChecked": "2022-07-11T00:00:00Z",
        "format": "hd",
        "mbps": "3188",
        "URI": [
            "s"
        ]
    },
    {
        "id": "2569719",
        "channel": "VERONICA / DISNEY XD (Test)",
        "link": "https://list.iptvcat.com/my_list/s/a49ff6140339fbd9ea3beb8223c66477.m3u8",
        "country": "netherlands",
        "liveliness": "95",
        "status": "online",
        "lastChecked": "2022-07-11T00:00:00Z",
        "format": "sd",
        "mbps": "2334",
        "URI": [
            "s"
        ]
    },
    {
        "id": "2490074",
        "channel": "VERONICA DISNEY XD",
        "link": "https://list.iptvcat.com/my_list/s/48c97edd44d337ffd32fb9cf784fd35f.m3u8",
        "country": "netherlands",
        "liveliness": "100",
        "status": "online",
        "lastChecked": "2022-07-11T00:00:00Z",
        "format": "sd",
        "mbps": "1736",
        "URI": [
            "s"
        ]
    },
    {
        "id": "2557394",
        "channel": "VERONICA/DISNEY XD FHD",
        "link": "https://list.iptvcat.com/my_list/s/6175bb9a1dc805dc4f678da7986dadcf.m3u8",
        "country": "netherlands",
        "liveliness": "95",
        "status": "online",
        "lastChecked": "2022-07-11T00:00:00Z",
        "format": "fhd 2k",
        "mbps": "7004",
        "URI": [
            "s"
        ]
    },
    {
        "id": "2557507",
        "channel": "VIP DISNEY CHANNEL HD",
        "link": "https://list.iptvcat.com/my_list/s/f32b82fc39c2b11b040d8c26859bc2a6.m3u8",
        "country": "netherlands",
        "liveliness": "66",
        "status": "offline",
        "lastChecked": "2022-07-11T00:00:00Z",
        "format": "fhd 2k",
        "mbps": "7004",
        "URI": [
            "s"
        ]
    },
    {
        "id": "2557568",
        "channel": "VIP DISNEY CHANNEL HEVC",
        "link": "https://list.iptvcat.com/my_list/s/45ba3ff301ea486051d5e4213167ec22.m3u8",
        "country": "netherlands",
        "liveliness": "92",
        "status": "online",
        "lastChecked": "2022-07-11T00:00:00Z",
        "format": "fhd 2k",
        "mbps": "11126",
        "URI": [
            "s"
        ]
    },
    {
        "id": "2557566",
        "channel": "VIP Veronica/DisneyXD HEVC",
        "link": "https://list.iptvcat.com/my_list/s/faf7791eb221b65d609cc746a0395e58.m3u8",
        "country": "netherlands",
        "liveliness": "96",
        "status": "online",
        "lastChecked": "2022-07-11T00:00:00Z",
        "format": "fhd 2k",
        "mbps": "11126",
        "URI": [
            "s"
        ]
    }
]